{"General": {"Code": "ZGM", "Type": "Common Stock", "Name": "Zenta Group Company Limited Ordinary Shares", "Exchange": "NASDAQ", "CurrencyCode": "USD", "CurrencyName": "US Dollar", "CurrencySymbol": "$", "CountryName": "USA", "CountryISO": "US", "OpenFigi": "BBG01RMMCFL6", "ISIN": "KYG988921055", "LEI": null, "PrimaryTicker": null, "CUSIP": null, "CIK": null, "EmployerIdNumber": null, "FiscalYearEnd": "September", "IPODate": "2025-09-09", "InternationalDomestic": null, "Sector": "Industrials", "Industry": "Consulting Services", "GicSector": "Industrials", "GicGroup": "Commercial & Professional Services", "GicIndustry": "Professional Services", "GicSubIndustry": "Research & Consulting Services", "HomeCategory": null, "IsDelisted": false, "Description": "Zenta Group Company Limited, together with its subsidiaries, engages in the provision of industrial park consultation and business investment consultation services; and sale of fintech products and services in Macau and the People's Republic of China. It offers fintech services to customers by offering algorithm and big data models and a blockchain system. The company's industrial park consultation services include project development consultation services; agency services of sales and leasing; property management and financial advisory services; advisory on operation improvement services; advisory on selection of suppliers/builders process services; and feasibility study report services. Its business investment consultation services comprise mergers and acquisitions consultation services; and administrative services, such as handling and managing corporate documents, maintaining and updating corporate changes and registrations, providing registered offices, and filing income tax returns. The company was incorporated in 2023 and is based in Macau.", "Address": "No. 47-53A, Macau Square, Macau, Macau, 999078", "AddressData": {"Street": "No. 47-53A, Macau Square", "City": "Macau", "Country": "Macau", "ZIP": "999078"}, "Listings": {}, "Officers": {"0": {"Name": "Mr. Wai Ian  Ng", "Title": "Founder, Chairman & CEO", "YearBorn": "1982"}, "1": {"Name": "Mr. Weng Seng  Sou", "Title": "Co-Founder, COO & Director", "YearBorn": "1980"}, "2": {"Name": "Mr. Fong Hang  Ieong", "Title": "Chief Financial Officer", "YearBorn": "1972"}, "3": {"Name": "Kong Pan  Chan", "Title": "Chief Strategy Officer", "YearBorn": "NA"}}, "Phone": "853 28400625", "WebURL": "https://zenta.com.mo", "LogoURL": "", "FullTimeEmployees": 9, "UpdatedAt": "2026-04-14"}, "Highlights": {"MarketCapitalization": 19484584, "MarketCapitalizationMln": 19.4846, "EBITDA": 1349381, "PERatio": 16.5, "PEGRatio": null, "WallStreetTargetPrice": null, "BookValue": 0.595, "DividendShare": null, "DividendYield": null, "EarningsShare": 0.1, "EPSEstimateCurrentYear": 0, "EPSEstimateNextYear": 0, "EPSEstimateNextQuarter": 0, "EPSEstimateCurrentQuarter": 0, "MostRecentQuarter": "2025-09-30", "ProfitMargin": 0.3166, "OperatingMarginTTM": 0.3168, "ReturnOnAssetsTTM": 0.1532, "ReturnOnEquityTTM": 0.2343, "RevenueTTM": 3163046, "RevenuePerShareTTM": 0.312, "QuarterlyRevenueGrowthYOY": -0.27, "GrossProfitTTM": 2469711, "DilutedEpsTTM": 0.1, "QuarterlyEarningsGrowthYOY": -0.78}, "Valuation": {"TrailingPE": 16.5, "ForwardPE": 0, "PriceSalesTTM": 6.1601, "PriceBookMRQ": 2.6376, "EnterpriseValue": 17216626, "EnterpriseValueRevenue": 5.4431, "EnterpriseValueEbitda": 9.7736}, "SharesStats": {"SharesOutstanding": 5441159, "SharesFloat": 3521478, "PercentInsiders": 44.590999999999994, "PercentInstitutions": 0.152, "SharesShort": null, "SharesShortPriorMonth": null, "ShortRatio": null, "ShortPercentOutstanding": null, "ShortPercentFloat": 0.0076}, "Technicals": {"Beta": null, "52WeekHigh": 4.51, "52WeekLow": 1.09, "50DayMA": 1.8138, "200DayMA": 2.5104, "SharesShort": 2509, "SharesShortPriorMonth": 32595, "ShortRatio": 6.63, "ShortPercent": 0.0076}, "SplitsDividends": {"ForwardAnnualDividendRate": 0, "ForwardAnnualDividendYield": 0, "PayoutRatio": 0, "DividendDate": null, "ExDividendDate": null, "LastSplitFactor": null, "LastSplitDate": null, "NumberDividendsByYear": {}}, "Holders": null, "InsiderTransactions": {}, "outstandingShares": {"annual": {"0": {"date": "2025", "dateFormatted": "2025-12-31", "sharesMln": "11.5838", "shares": 11583800}, "1": {"date": "2024", "dateFormatted": "2024-12-31", "sharesMln": "11.5838", "shares": 11583800}}, "quarterly": {"0": {"date": "2025-Q3", "dateFormatted": "2025-09-30", "sharesMln": "11.5838", "shares": 11583800}, "1": {"date": "2025-Q1", "dateFormatted": "2025-03-31", "sharesMln": "11.5838", "shares": 11583800}, "2": {"date": "2024-Q3", "dateFormatted": "2024-09-30", "sharesMln": "11.5838", "shares": 11583800}, "3": {"date": "2024-Q1", "dateFormatted": "2024-03-31", "sharesMln": "11.5838", "shares": 11583800}}}, "Earnings": {"History": {"2025-06-30": {"reportDate": "2025-07-24", "date": "2025-06-30", "beforeAfterMarket": null, "currency": null, "epsActual": 0.08, "epsEstimate": 0, "epsDifference": 0.08, "surprisePercent": null}}, "Trend": {}, "Annual": {"2025-06-30": {"date": "2025-06-30", "epsActual": 0.08}}}, "Financials": {"Balance_Sheet": {"currency_symbol": "USD", "quarterly": {"2025-09-30": {"date": "2025-09-30", "filing_date": null, "currency_symbol": "USD", "totalAssets": "7324715.00", "intangibleAssets": "901035.00", "earningAssets": null, "otherCurrentAssets": "139687.00", "totalLiab": "429970.00", "totalStockholderEquity": "6894745.00", "deferredLongTermLiab": null, "otherCurrentLiab": "128390.00", "commonStock": null, "capitalStock": "11584.00", "retainedEarnings": "2101998.00", "otherLiab": null, "goodWill": null, "otherAssets": null, "cash": "1042230.00", "cashAndEquivalents": null, "totalCurrentLiabilities": "424262.00", "currentDeferredRevenue": null, "netDebt": null, "shortTermDebt": null, "shortLongTermDebt": null, "shortLongTermDebtTotal": null, "otherStockholderEquity": null, "propertyPlantEquipment": null, "totalCurrentAssets": "3456937.00", "longTermInvestments": null, "netTangibleAssets": null, "shortTermInvestments": null, "netReceivables": "594549.00", "longTermDebt": null, "inventory": null, "accountsPayable": "0.00", "totalPermanentEquity": null, "noncontrollingInterestInConsolidatedEntity": null, "temporaryEquityRedeemableNoncontrollingInterests": null, "accumulatedOtherComprehensiveIncome": null, "additionalPaidInCapital": null, "commonStockTotalEquity": null, "preferredStockTotalEquity": null, "retainedEarningsTotalEquity": null, "treasuryStock": null, "accumulatedAmortization": null, "nonCurrrentAssetsOther": null, "deferredLongTermAssetCharges": null, "nonCurrentAssetsTotal": "3867778.00", "capitalLeaseObligations": "73245.00", "longTermDebtTotal": null, "nonCurrentLiabilitiesOther": null, "nonCurrentLiabilitiesTotal": "5708.00", "negativeGoodwill": null, "warrants": null, "preferredStockRedeemable": null, "capitalSurpluse": null, "liabilitiesAndStockholdersEquity": null, "cashAndShortTermInvestments": null, "propertyPlantAndEquipmentGross": "74740.00", "propertyPlantAndEquipmentNet": "71316.00", "accumulatedDepreciation": null, "netWorkingCapital": "3032675.00", "netInvestedCapital": "6894745.00", "commonStockSharesOutstanding": "11583839.00"}, "2025-03-31": {"date": "2025-03-31", "filing_date": null, "currency_symbol": "USD", "totalAssets": "2852881.00", "intangibleAssets": "899923.00", "earningAssets": null, "otherCurrentAssets": null, "totalLiab": "413253.00", "totalStockholderEquity": "2439628.00", "deferredLongTermLiab": null, "otherCurrentLiab": null, "commonStock": null, "capitalStock": "10084.00", "retainedEarnings": "1890054.00", "otherLiab": null, "goodWill": null, "otherAssets": null, "cash": "188486.00", "cashAndEquivalents": null, "totalCurrentLiabilities": "373533.00", "currentDeferredRevenue": null, "netDebt": null, "shortTermDebt": null, "shortLongTermDebt": null, "shortLongTermDebtTotal": null, "otherStockholderEquity": null, "propertyPlantEquipment": null, "totalCurrentAssets": "1081724.00", "longTermInvestments": null, "netTangibleAssets": null, "shortTermInvestments": null, "netReceivables": "507131.00", "longTermDebt": null, "inventory": null, "accountsPayable": "0.00", "totalPermanentEquity": null, "noncontrollingInterestInConsolidatedEntity": null, "temporaryEquityRedeemableNoncontrollingInterests": null, "accumulatedOtherComprehensiveIncome": null, "additionalPaidInCapital": null, "commonStockTotalEquity": null, "preferredStockTotalEquity": null, "retainedEarningsTotalEquity": null, "treasuryStock": null, "accumulatedAmortization": null, "nonCurrrentAssetsOther": null, "deferredLongTermAssetCharges": null, "nonCurrentAssetsTotal": "1771157.00", "capitalLeaseObligations": "106414.00", "longTermDebtTotal": null, "nonCurrentLiabilitiesOther": null, "nonCurrentLiabilitiesTotal": "39720.00", "negativeGoodwill": null, "warrants": null, "preferredStockRedeemable": null, "capitalSurpluse": null, "liabilitiesAndStockholdersEquity": null, "cashAndShortTermInvestments": null, "propertyPlantAndEquipmentGross": "106776.00", "propertyPlantAndEquipmentNet": "104087.00", "accumulatedDepreciation": null, "netWorkingCapital": "708191.00", "netInvestedCapital": "2439628.00", "commonStockSharesOutstanding": "11583839.00"}, "2024-09-30": {"date": "2024-09-30", "filing_date": null, "currency_symbol": "USD", "totalAssets": "3672840.00", "intangibleAssets": "1093896.00", "earningAssets": null, "otherCurrentAssets": null, "totalLiab": "2020721.00", "totalStockholderEquity": "1652119.00", "deferredLongTermLiab": null, "otherCurrentLiab": "113380.00", "commonStock": null, "capitalStock": "10084.00", "retainedEarnings": "1100663.00", "otherLiab": null, "goodWill": null, "otherAssets": null, "cash": "327111.00", "cashAndEquivalents": null, "totalCurrentLiabilities": "2020721.00", "currentDeferredRevenue": null, "netDebt": null, "shortTermDebt": null, "shortLongTermDebt": null, "shortLongTermDebtTotal": null, "otherStockholderEquity": null, "propertyPlantEquipment": null, "totalCurrentAssets": "1993828.00", "longTermInvestments": null, "netTangibleAssets": null, "shortTermInvestments": null, "netReceivables": "1642654.00", "longTermDebt": null, "inventory": null, "accountsPayable": "154236.00", "totalPermanentEquity": null, "noncontrollingInterestInConsolidatedEntity": null, "temporaryEquityRedeemableNoncontrollingInterests": null, "accumulatedOtherComprehensiveIncome": null, "additionalPaidInCapital": null, "commonStockTotalEquity": null, "preferredStockTotalEquity": null, "retainedEarningsTotalEquity": null, "treasuryStock": null, "accumulatedAmortization": null, "nonCurrrentAssetsOther": null, "deferredLongTermAssetCharges": null, "nonCurrentAssetsTotal": "1679012.00", "capitalLeaseObligations": "6890.00", "longTermDebtTotal": null, "nonCurrentLiabilitiesOther": null, "nonCurrentLiabilitiesTotal": "0.00", "negativeGoodwill": null, "warrants": null, "preferredStockRedeemable": null, "capitalSurpluse": null, "liabilitiesAndStockholdersEquity": null, "cashAndShortTermInvestments": null, "propertyPlantAndEquipmentGross": "12185.00", "propertyPlantAndEquipmentNet": "10231.00", "accumulatedDepreciation": null, "netWorkingCapital": "-26893.00", "netInvestedCapital": "1652119.00", "commonStockSharesOutstanding": "11583839.00"}, "2024-03-31": {"date": "2024-03-31", "filing_date": null, "currency_symbol": "USD", "totalAssets": "1151983.00", "intangibleAssets": null, "earningAssets": null, "otherCurrentAssets": null, "totalLiab": "466340.00", "totalStockholderEquity": "685643.00", "deferredLongTermLiab": null, "otherCurrentLiab": null, "commonStock": null, "capitalStock": "10084.00", "retainedEarnings": "144122.00", "otherLiab": null, "goodWill": null, "otherAssets": null, "cash": "347643.00", "cashAndEquivalents": null, "totalCurrentLiabilities": "466340.00", "currentDeferredRevenue": null, "netDebt": null, "shortTermDebt": null, "shortLongTermDebt": null, "shortLongTermDebtTotal": null, "otherStockholderEquity": null, "propertyPlantEquipment": null, "totalCurrentAssets": "858351.00", "longTermInvestments": null, "netTangibleAssets": null, "shortTermInvestments": null, "netReceivables": "485639.00", "longTermDebt": null, "inventory": null, "accountsPayable": "165496.00", "totalPermanentEquity": null, "noncontrollingInterestInConsolidatedEntity": null, "temporaryEquityRedeemableNoncontrollingInterests": null, "accumulatedOtherComprehensiveIncome": null, "additionalPaidInCapital": null, "commonStockTotalEquity": null, "preferredStockTotalEquity": null, "retainedEarningsTotalEquity": null, "treasuryStock": null, "accumulatedAmortization": null, "nonCurrrentAssetsOther": null, "deferredLongTermAssetCharges": null, "nonCurrentAssetsTotal": "293632.00", "capitalLeaseObligations": "47561.00", "longTermDebtTotal": null, "nonCurrentLiabilitiesOther": null, "nonCurrentLiabilitiesTotal": "0.00", "negativeGoodwill": null, "warrants": null, "preferredStockRedeemable": null, "capitalSurpluse": null, "liabilitiesAndStockholdersEquity": null, "cashAndShortTermInvestments": null, "propertyPlantAndEquipmentGross": "52147.00", "propertyPlantAndEquipmentNet": "50940.00", "accumulatedDepreciation": null, "netWorkingCapital": "392011.00", "netInvestedCapital": "685643.00", "commonStockSharesOutstanding": "11583839.00"}}, "yearly": {"2025-09-30": {"date": "2025-09-30", "filing_date": null, "currency_symbol": "USD", "totalAssets": "7324715.00", "intangibleAssets": "901035.00", "earningAssets": null, "otherCurrentAssets": "139687.00", "totalLiab": "429970.00", "totalStockholderEquity": "6894745.00", "deferredLongTermLiab": null, "otherCurrentLiab": "128390.00", "commonStock": null, "capitalStock": "11584.00", "retainedEarnings": "2101998.00", "otherLiab": null, "goodWill": null, "otherAssets": null, "cash": "1042230.00", "cashAndEquivalents": null, "totalCurrentLiabilities": "424262.00", "currentDeferredRevenue": null, "netDebt": null, "shortTermDebt": null, "shortLongTermDebt": null, "shortLongTermDebtTotal": null, "otherStockholderEquity": null, "propertyPlantEquipment": null, "totalCurrentAssets": "3456937.00", "longTermInvestments": null, "netTangibleAssets": null, "shortTermInvestments": null, "netReceivables": "594549.00", "longTermDebt": null, "inventory": null, "accountsPayable": "0.00", "totalPermanentEquity": null, "noncontrollingInterestInConsolidatedEntity": null, "temporaryEquityRedeemableNoncontrollingInterests": null, "accumulatedOtherComprehensiveIncome": null, "additionalPaidInCapital": null, "commonStockTotalEquity": null, "preferredStockTotalEquity": null, "retainedEarningsTotalEquity": null, "treasuryStock": null, "accumulatedAmortization": null, "nonCurrrentAssetsOther": null, "deferredLongTermAssetCharges": null, "nonCurrentAssetsTotal": "3867778.00", "capitalLeaseObligations": "73245.00", "longTermDebtTotal": null, "nonCurrentLiabilitiesOther": null, "nonCurrentLiabilitiesTotal": "5708.00", "negativeGoodwill": null, "warrants": null, "preferredStockRedeemable": null, "capitalSurpluse": null, "liabilitiesAndStockholdersEquity": "7324715.00", "cashAndShortTermInvestments": null, "propertyPlantAndEquipmentGross": "74740.00", "propertyPlantAndEquipmentNet": "71316.00", "accumulatedDepreciation": null, "netWorkingCapital": "3032675.00", "netInvestedCapital": "6894745.00", "commonStockSharesOutstanding": "11583839.00"}, "2024-09-30": {"date": "2024-09-30", "filing_date": "2024-09-30", "currency_symbol": "USD", "totalAssets": "3672840.00", "intangibleAssets": "1093896.00", "earningAssets": null, "otherCurrentAssets": "24050.00", "totalLiab": "2020721.00", "totalStockholderEquity": "1652119.00", "deferredLongTermLiab": null, "otherCurrentLiab": "1640673.00", "commonStock": "10084.00", "capitalStock": "10084.00", "retainedEarnings": "1100663.00", "otherLiab": null, "goodWill": null, "otherAssets": null, "cash": "327111.00", "cashAndEquivalents": null, "totalCurrentLiabilities": "2020721.00", "currentDeferredRevenue": null, "netDebt": "-320221.00", "shortTermDebt": "6890.00", "shortLongTermDebt": null, "shortLongTermDebtTotal": "6890.00", "otherStockholderEquity": "529963.00", "propertyPlantEquipment": null, "totalCurrentAssets": "1993828.00", "longTermInvestments": null, "netTangibleAssets": null, "shortTermInvestments": null, "netReceivables": "1642667.00", "longTermDebt": null, "inventory": null, "accountsPayable": "154236.00", "totalPermanentEquity": null, "noncontrollingInterestInConsolidatedEntity": null, "temporaryEquityRedeemableNoncontrollingInterests": null, "accumulatedOtherComprehensiveIncome": "11409.00", "additionalPaidInCapital": null, "commonStockTotalEquity": null, "preferredStockTotalEquity": null, "retainedEarningsTotalEquity": null, "treasuryStock": null, "accumulatedAmortization": null, "nonCurrrentAssetsOther": "574865.00", "deferredLongTermAssetCharges": null, "nonCurrentAssetsTotal": "1679012.00", "capitalLeaseObligations": "6890.00", "longTermDebtTotal": null, "nonCurrentLiabilitiesOther": null, "nonCurrentLiabilitiesTotal": "0.00", "negativeGoodwill": null, "warrants": null, "preferredStockRedeemable": null, "capitalSurpluse": null, "liabilitiesAndStockholdersEquity": "3672840.00", "cashAndShortTermInvestments": "327111.00", "propertyPlantAndEquipmentGross": "12185.00", "propertyPlantAndEquipmentNet": "10231.00", "accumulatedDepreciation": null, "netWorkingCapital": "-26893.00", "netInvestedCapital": "1652119.00", "commonStockSharesOutstanding": "11583839.00"}, "2023-09-30": {"date": "2023-09-30", "filing_date": "2023-09-30", "currency_symbol": "USD", "totalAssets": "799402.00", "intangibleAssets": null, "earningAssets": null, "otherCurrentAssets": "23776.00", "totalLiab": "222169.00", "totalStockholderEquity": "577233.00", "deferredLongTermLiab": null, "otherCurrentLiab": "85680.00", "commonStock": "10075.00", "capitalStock": "10075.00", "retainedEarnings": "301947.00", "otherLiab": null, "goodWill": null, "otherAssets": null, "cash": "524383.00", "cashAndEquivalents": null, "totalCurrentLiabilities": "215331.00", "currentDeferredRevenue": null, "netDebt": "-436758.00", "shortTermDebt": "80787.00", "shortLongTermDebt": null, "shortLongTermDebtTotal": "87625.00", "otherStockholderEquity": "264500.00", "propertyPlantEquipment": null, "totalCurrentAssets": "548179.00", "longTermInvestments": null, "netTangibleAssets": null, "shortTermInvestments": null, "netReceivables": "20.00", "longTermDebt": null, "inventory": null, "accountsPayable": "0.00", "totalPermanentEquity": null, "noncontrollingInterestInConsolidatedEntity": null, "temporaryEquityRedeemableNoncontrollingInterests": null, "accumulatedOtherComprehensiveIncome": "711.00", "additionalPaidInCapital": null, "commonStockTotalEquity": null, "preferredStockTotalEquity": null, "retainedEarningsTotalEquity": null, "treasuryStock": null, "accumulatedAmortization": null, "nonCurrrentAssetsOther": "159471.00", "deferredLongTermAssetCharges": null, "nonCurrentAssetsTotal": "251223.00", "capitalLeaseObligations": "87625.00", "longTermDebtTotal": null, "nonCurrentLiabilitiesOther": null, "nonCurrentLiabilitiesTotal": "6838.00", "negativeGoodwill": null, "warrants": null, "preferredStockRedeemable": null, "capitalSurpluse": null, "liabilitiesAndStockholdersEquity": "799402.00", "cashAndShortTermInvestments": "524383.00", "propertyPlantAndEquipmentGross": "92114.00", "propertyPlantAndEquipmentNet": "91640.00", "accumulatedDepreciation": null, "netWorkingCapital": "332848.00", "netInvestedCapital": "577233.00", "commonStockSharesOutstanding": "11583839.00"}, "2022-09-30": {"date": "2022-09-30", "filing_date": "2022-09-30", "currency_symbol": "USD", "totalAssets": "196779.00", "intangibleAssets": null, "earningAssets": null, "otherCurrentAssets": "17490.00", "totalLiab": "313481.00", "totalStockholderEquity": "-116702.00", "deferredLongTermLiab": null, "otherCurrentLiab": "291113.00", "commonStock": "10000.00", "capitalStock": "10000.00", "retainedEarnings": "-117611.00", "otherLiab": null, "goodWill": null, "otherAssets": null, "cash": "52896.00", "cashAndEquivalents": null, "totalCurrentLiabilities": "313481.00", "currentDeferredRevenue": null, "netDebt": "-30528.00", "shortTermDebt": "22368.00", "shortLongTermDebt": null, "shortLongTermDebtTotal": "22368.00", "otherStockholderEquity": "-10000.00", "propertyPlantEquipment": null, "totalCurrentAssets": "174795.00", "longTermInvestments": null, "netTangibleAssets": null, "shortTermInvestments": null, "netReceivables": "104409.00", "longTermDebt": null, "inventory": null, "accountsPayable": null, "totalPermanentEquity": null, "noncontrollingInterestInConsolidatedEntity": null, "temporaryEquityRedeemableNoncontrollingInterests": null, "accumulatedOtherComprehensiveIncome": "909.00", "additionalPaidInCapital": null, "commonStockTotalEquity": null, "preferredStockTotalEquity": null, "retainedEarningsTotalEquity": null, "treasuryStock": null, "accumulatedAmortization": null, "nonCurrrentAssetsOther": null, "deferredLongTermAssetCharges": null, "nonCurrentAssetsTotal": "21984.00", "capitalLeaseObligations": "22368.00", "longTermDebtTotal": null, "nonCurrentLiabilitiesOther": null, "nonCurrentLiabilitiesTotal": "0.00", "negativeGoodwill": null, "warrants": null, "preferredStockRedeemable": null, "capitalSurpluse": null, "liabilitiesAndStockholdersEquity": "196779.00", "cashAndShortTermInvestments": "52896.00", "propertyPlantAndEquipmentGross": "21932.00", "propertyPlantAndEquipmentNet": "21932.00", "accumulatedDepreciation": null, "netWorkingCapital": "-138686.00", "netInvestedCapital": "-116702.00", "commonStockSharesOutstanding": "11583839.00"}}}, "Cash_Flow": {"currency_symbol": "USD", "quarterly": {}, "yearly": {"2025-09-30": {"date": "2025-09-30", "filing_date": null, "currency_symbol": "USD", "investments": null, "changeToLiabilities": null, "totalCashflowsFromInvestingActivities": null, "netBorrowings": null, "totalCashFromFinancingActivities": "4588829.00", "changeToOperatingActivities": null, "netIncome": "1001335.00", "changeInCash": "715119.00", "beginPeriodCashFlow": "327111.00", "endPeriodCashFlow": "1042230.00", "totalCashFromOperatingActivities": "-3662588.00", "issuanceOfCapitalStock": "5247354.00", "depreciation": "470512.00", "otherCashflowsFromInvestingActivities": null, "dividendsPaid": null, "changeToInventory": null, "changeToAccountReceivables": "1061513.00", "salePurchaseOfStock": null, "otherCashflowsFromFinancingActivities": null, "changeToNetincome": null, "capitalExpenditures": "211688", "changeReceivables": null, "cashFlowsOtherOperating": null, "exchangeRateChanges": null, "cashAndCashEquivalentsChanges": null, "changeInWorkingCapital": "-5118688.00", "stockBasedCompensation": null, "otherNonCashItems": null, "freeCashFlow": "-3874276.00"}, "2024-09-30": {"date": "2024-09-30", "filing_date": "2024-09-30", "currency_symbol": "USD", "investments": "0.00", "changeToLiabilities": null, "totalCashflowsFromInvestingActivities": null, "netBorrowings": null, "totalCashFromFinancingActivities": "140254.00", "changeToOperatingActivities": null, "netIncome": "798716.00", "changeInCash": "-197272.00", "beginPeriodCashFlow": "524383.00", "endPeriodCashFlow": "327111.00", "totalCashFromOperatingActivities": "-340501.00", "issuanceOfCapitalStock": "0.00", "depreciation": "146954.00", "otherCashflowsFromInvestingActivities": null, "dividendsPaid": null, "changeToInventory": null, "changeToAccountReceivables": "-1655244.00", "salePurchaseOfStock": null, "otherCashflowsFromFinancingActivities": "140254.00", "changeToNetincome": null, "capitalExpenditures": "0", "changeReceivables": null, "cashFlowsOtherOperating": null, "exchangeRateChanges": null, "cashAndCashEquivalentsChanges": null, "changeInWorkingCapital": "-1307584.00", "stockBasedCompensation": null, "otherNonCashItems": "21321.00", "freeCashFlow": "-340501.00"}, "2023-09-30": {"date": "2023-09-30", "filing_date": "2023-09-30", "currency_symbol": "USD", "investments": "-5421.00", "changeToLiabilities": null, "totalCashflowsFromInvestingActivities": "-5421.00", "netBorrowings": null, "totalCashFromFinancingActivities": "-91752.00", "changeToOperatingActivities": null, "netIncome": "419558.00", "changeInCash": "471487.00", "beginPeriodCashFlow": "52896.00", "endPeriodCashFlow": "524383.00", "totalCashFromOperatingActivities": "568405.00", "issuanceOfCapitalStock": "0.00", "depreciation": "84951.00", "otherCashflowsFromInvestingActivities": null, "dividendsPaid": null, "changeToInventory": null, "changeToAccountReceivables": "104694.00", "salePurchaseOfStock": null, "otherCashflowsFromFinancingActivities": "-91752.00", "changeToNetincome": null, "capitalExpenditures": "5421", "changeReceivables": null, "cashFlowsOtherOperating": null, "exchangeRateChanges": null, "cashAndCashEquivalentsChanges": null, "changeInWorkingCapital": "64026.00", "stockBasedCompensation": null, "otherNonCashItems": "-71.00", "freeCashFlow": "562984.00"}, "2022-09-30": {"date": "2022-09-30", "filing_date": "2022-09-30", "currency_symbol": "USD", "investments": "0.00", "changeToLiabilities": null, "totalCashflowsFromInvestingActivities": null, "netBorrowings": null, "totalCashFromFinancingActivities": "212146.00", "changeToOperatingActivities": null, "netIncome": "-65244.00", "changeInCash": "39911.00", "beginPeriodCashFlow": "12985.00", "endPeriodCashFlow": "52896.00", "totalCashFromOperatingActivities": "-172003.00", "issuanceOfCapitalStock": null, "depreciation": "89430.00", "otherCashflowsFromInvestingActivities": null, "dividendsPaid": null, "changeToInventory": null, "changeToAccountReceivables": "-104789.00", "salePurchaseOfStock": null, "otherCashflowsFromFinancingActivities": "212146.00", "changeToNetincome": null, "capitalExpenditures": "0", "changeReceivables": null, "cashFlowsOtherOperating": null, "exchangeRateChanges": null, "cashAndCashEquivalentsChanges": null, "changeInWorkingCapital": "-196334.00", "stockBasedCompensation": null, "otherNonCashItems": "86.00", "freeCashFlow": "-172003.00"}}}, "Income_Statement": {"currency_symbol": "USD", "quarterly": {}, "yearly": {"2025-09-30": {"date": "2025-09-30", "filing_date": null, "currency_symbol": "USD", "researchDevelopment": "33405.00", "effectOfAccountingCharges": null, "incomeBeforeTax": "1290469.00", "minorityInterest": null, "netIncome": "1001335.00", "sellingGeneralAdministrative": "513987.00", "sellingAndMarketingExpenses": null, "grossProfit": "2469711.00", "reconciledDepreciation": "470512.00", "ebit": null, "ebitda": null, "depreciationAndAmortization": null, "nonOperatingIncomeNetOther": null, "operatingIncome": "1347910.00", "otherOperatingExpenses": null, "interestExpense": "558.00", "taxProvision": "289134.00", "interestIncome": "386.00", "netInterestIncome": "-172.00", "extraordinaryItems": null, "nonRecurring": null, "otherItems": null, "incomeTaxExpense": null, "totalRevenue": "3163046.00", "totalOperatingExpenses": "1815136.00", "costOfRevenue": "693335.00", "totalOtherIncomeExpenseNet": "-57269.00", "discontinuedOperations": null, "netIncomeFromContinuingOps": "1001335.00", "netIncomeApplicableToCommonShares": null, "preferredStockAndOtherAdjustments": null}, "2024-09-30": {"date": "2024-09-30", "filing_date": "2024-09-30", "currency_symbol": "USD", "researchDevelopment": "16599.00", "effectOfAccountingCharges": null, "incomeBeforeTax": "980866.00", "minorityInterest": null, "netIncome": "798716.00", "sellingGeneralAdministrative": "480516.00", "sellingAndMarketingExpenses": null, "grossProfit": "1562804.00", "reconciledDepreciation": "146954.00", "ebit": "978894.00", "ebitda": "1125848.00", "depreciationAndAmortization": "146954.00", "nonOperatingIncomeNetOther": null, "operatingIncome": "978894.00", "otherOperatingExpenses": "1049989.00", "interestExpense": null, "taxProvision": "182150.00", "interestIncome": "1972.00", "netInterestIncome": "1972.00", "extraordinaryItems": null, "nonRecurring": null, "otherItems": null, "incomeTaxExpense": "182150.00", "totalRevenue": "2028883.00", "totalOperatingExpenses": "583910.00", "costOfRevenue": "466079.00", "totalOtherIncomeExpenseNet": "1972.00", "discontinuedOperations": null, "netIncomeFromContinuingOps": "798716.00", "netIncomeApplicableToCommonShares": null, "preferredStockAndOtherAdjustments": null}, "2023-09-30": {"date": "2023-09-30", "filing_date": "2023-09-30", "currency_symbol": "USD", "researchDevelopment": "33715.00", "effectOfAccountingCharges": null, "incomeBeforeTax": "468350.00", "minorityInterest": null, "netIncome": "419558.00", "sellingGeneralAdministrative": "184640.00", "sellingAndMarketingExpenses": null, "grossProfit": "686534.00", "reconciledDepreciation": "84951.00", "ebit": "467776.00", "ebitda": "552727.00", "depreciationAndAmortization": "84951.00", "nonOperatingIncomeNetOther": null, "operatingIncome": "467776.00", "otherOperatingExpenses": "394878.00", "interestExpense": null, "taxProvision": "48792.00", "interestIncome": "574.00", "netInterestIncome": "574.00", "extraordinaryItems": null, "nonRecurring": null, "otherItems": null, "incomeTaxExpense": "48792.00", "totalRevenue": "862654.00", "totalOperatingExpenses": "218758.00", "costOfRevenue": "176120.00", "totalOtherIncomeExpenseNet": "574.00", "discontinuedOperations": null, "netIncomeFromContinuingOps": "419558.00", "netIncomeApplicableToCommonShares": null, "preferredStockAndOtherAdjustments": null}, "2022-09-30": {"date": "2022-09-30", "filing_date": "2022-09-30", "currency_symbol": "USD", "researchDevelopment": "6238.00", "effectOfAccountingCharges": null, "incomeBeforeTax": "-65185.00", "minorityInterest": null, "netIncome": "-65244.00", "sellingGeneralAdministrative": "117979.00", "sellingAndMarketingExpenses": null, "grossProfit": "53020.00", "reconciledDepreciation": "89430.00", "ebit": "-65377.00", "ebitda": "24053.00", "depreciationAndAmortization": "89430.00", "nonOperatingIncomeNetOther": null, "operatingIncome": "-65377.00", "otherOperatingExpenses": "237164.00", "interestExpense": null, "taxProvision": "59.00", "interestIncome": "192.00", "netInterestIncome": "192.00", "extraordinaryItems": null, "nonRecurring": null, "otherItems": null, "incomeTaxExpense": "59.00", "totalRevenue": "171787.00", "totalOperatingExpenses": "118397.00", "costOfRevenue": "118767.00", "totalOtherIncomeExpenseNet": "192.00", "discontinuedOperations": null, "netIncomeFromContinuingOps": "-65244.00", "netIncomeApplicableToCommonShares": null, "preferredStockAndOtherAdjustments": null}}}}}